<?xml version="1.0"?>
<?xml-stylesheet type="text/xsl"  href="configuration.xsl"?>
<configuration>
    <property>
        <name>ape.features.dir</name>
        <value>/eyeCloudAI/data/processing/ape/division</value>
    </property>
    <property>
        <name>kubernetes.log.debug.yn</name>
        <value>N</value>
    </property>
    <property>
        <name>kube.pod.cpu.limit</name>
        <value>1200</value>
        <description>m</description>
    </property>
    <property>
        <name>kube.pod.memory.limit</name>
        <value>0</value>
        <description>Gi</description>
    </property>
</configuration>
